.DS_Store
Autotest_api/__init__.py
Autotest_api/create_funtion.py
Autotest_api/db.py
Autotest_api/exceptions.py
Autotest_api/extract.py
Autotest_api/http_session.py
Autotest_api/log.py
Autotest_api/mitm_http.py
Autotest_api/my_builtins.py
Autotest_api/parser.py
Autotest_api/plugin.py
Autotest_api/render_template_obj.py
Autotest_api/report_notify.py
Autotest_api/request_session.py
Autotest_api/runner.py
Autotest_api/start_project.py
Autotest_api/swagger_parser.py
Autotest_api/validate.py
Autotest_api-1.5.2.dist-info/METADATA
Autotest_api-1.5.2.dist-info/WHEEL
Autotest_api-1.5.2.dist-info/entry_points.txt
Autotest_api-1.5.2.dist-info/top_level.txt
Autotest_api-1.5.2.dist-info/RECORD
