Metadata-Version: 2.1
Name: Autotest-api
Version: 1.5.2
Summary: http/https API run by yaml
Home-page: https://github.com/leo/Autotest_api
Author: Prince
Author-email: 994991952@qq.com
License: proprietary
Keywords: pytest,py.test,pytest-yaml,Autotest_api
Classifier: Framework :: Pytest
Classifier: Programming Language :: Python
Classifier: Topic :: Software Development :: Testing
Classifier: Programming Language :: Python :: 3.9
Requires-Python: >=3.9
Requires-Dist: Jinja2 (>=3.1.2)
Requires-Dist: jmespath (>=0.9.5)
Requires-Dist: jsonpath (>=0.82)
Requires-Dist: pytest (>=7.2.0)
Requires-Dist: PyYAML (>=6.0)
Requires-Dist: requests (==2.18.4)
Requires-Dist: allure-pytest (>=2.12.0)
Requires-Dist: pymysql (>=1.0.2)
Requires-Dist: DingtalkChatbot (>=1.5.7)
Requires-Dist: Faker (>=15.3.4)
Requires-Dist: requests-toolbelt (>=0.10.1)
Requires-Dist: redis (>=4.6.0)
Requires-Dist: websocket-client (>=1.6.1)
Requires-Dist: websockets (>=11.0.3)
Requires-Dist: pydantic (<2.0)
Requires-Dist: pytest-runtime-yoyo (>=1.0.1)
